myCalculatorPackage123/__init__.py
myCalculatorPackage123/division/__init__.py
myCalculatorPackage123/division/divide.py
myCalculatorPackage123/multiplication/__init__.py
myCalculatorPackage123/multiplication/multiply.py
myCalculatorPackage123-0.0.2.dist-info/LICENSE.txt
myCalculatorPackage123-0.0.2.dist-info/METADATA
myCalculatorPackage123-0.0.2.dist-info/WHEEL
myCalculatorPackage123-0.0.2.dist-info/top_level.txt
myCalculatorPackage123-0.0.2.dist-info/RECORD
